tests/__init__.py
tests/context.py
tests/test_cache.py
tests/test_datetime-assumptions.py
tests/test_market_intervals_asx.py
tests/test_market_intervals_nze.py
tests/test_market_intervals_tlv.py
tests/test_market_intervals_usa.py
tests/test_market_schedules_asx.py
tests/test_market_schedules_nze.py
tests/test_market_schedules_tlv.py
tests/test_market_schedules_usa.py
tests/test_missing_intervals_asx.py
tests/test_missing_intervals_nze.py
tests/test_missing_intervals_tlv.py
tests/test_missing_intervals_usa.py
tests/test_price_data_aging_1d.py
tests/test_price_data_aging_1h.py
tests/test_price_data_aging_1w.py
tests/test_time_utils.py
tests/test_utils.py
tests/test_yf_assumptions.py
tests/test_yfc_adjust.py
tests/test_yfc_backend.py
tests/test_yfc_financials.py
tests/test_yfc_interface.py
tests/test_yfc_ticker.py
tests/utils.py
yfinance_cache/__init__.py
yfinance_cache/yfc_cache_manager.py
yfinance_cache/yfc_dat.py
yfinance_cache/yfc_financials_manager.py
yfinance_cache/yfc_logging.py
yfinance_cache/yfc_multi.py
yfinance_cache/yfc_prices_manager.py
yfinance_cache/yfc_ticker.py
yfinance_cache/yfc_time.py
yfinance_cache/yfc_upgrade.py
yfinance_cache/yfc_utils.py
yfinance_cache-0.7.12.dist-info/licenses/LICENSE
yfinance_cache-0.7.12.dist-info/METADATA
yfinance_cache-0.7.12.dist-info/WHEEL
yfinance_cache-0.7.12.dist-info/top_level.txt
yfinance_cache-0.7.12.dist-info/RECORD
