Metadata-Version: 2.4
Name: yfinance-cache
Version: 0.7.12
Summary: Smart caching wrapper for 'yfinance' module
Home-page: https://github.com/ValueRaider/yfinance-cache
Author: ValueRaider
Author-email: ValueRaider@protonmail.com
Project-URL: Bug Tracker, https://github.com/ValueRaider/yfinance-cache/issues
Classifier: Programming Language :: Python :: 3
Classifier: License :: OSI Approved :: MIT License
Classifier: Operating System :: OS Independent
Requires-Python: >=3.9
License-File: LICENSE
Requires-Dist: yfinance>=0.2.57
Requires-Dist: exchange_calendars>=4.10
Requires-Dist: numpy>=1.26
Requires-Dist: pandas>=1.5
Requires-Dist: scipy>=1.6.3
Requires-Dist: platformdirs
Requires-Dist: pulp
Dynamic: license-file
